CHANGELOG.md
LICENSE
MANIFEST.in
README.md
pyproject.toml
requirements.txt
setup.py
examples/exemplo_basico.py
examples/exemplo_ecommerce.py
examples/exemplo_env.py
examples/exemplo_webhook.py
pixgo/__init__.py
pixgo/client.py
pixgo/exceptions.py
pixgo/models.py
pixgo.egg-info/PKG-INFO
pixgo.egg-info/SOURCES.txt
pixgo.egg-info/dependency_links.txt
pixgo.egg-info/requires.txt
pixgo.egg-info/top_level.txt
tests/__init__.py
tests/test_client.py