Metadata-Version: 2.4
Name: pixgo
Version: 1.0.0
Summary: Cliente Python para integração com a API de pagamentos PIX do PixGo
Home-page: https://github.com/DevWand/pixgo-python
Author: PixGo Python Client
License: MIT
Project-URL: Homepage, https://github.com/DevWand/pixgo-python
Project-URL: Documentation, https://pixgo.org/api/v1/docs
Project-URL: Repository, https://github.com/DevWand/pixgo-python
Project-URL: Bug Tracker, https://github.com/DevWand/pixgo-python/issues
Keywords: pixgo,pix,pagamentos,api,brasil,payment
Classifier: Development Status :: 4 - Beta
Classifier: Intended Audience :: Developers
Classifier: License :: OSI Approved :: MIT License
Classifier: Programming Language :: Python :: 3
Classifier: Programming Language :: Python :: 3.7
Classifier: Programming Language :: Python :: 3.8
Classifier: Programming Language :: Python :: 3.9
Classifier: Programming Language :: Python :: 3.10
Classifier: Programming Language :: Python :: 3.11
Classifier: Programming Language :: Python :: 3.12
Classifier: Topic :: Software Development :: Libraries :: Python Modules
Classifier: Topic :: Office/Business :: Financial
Requires-Python: >=3.7
License-File: LICENSE
Requires-Dist: requests>=2.25.0
Provides-Extra: dev
Requires-Dist: pytest>=7.0.0; extra == "dev"
Requires-Dist: pytest-cov>=3.0.0; extra == "dev"
Requires-Dist: black>=22.0.0; extra == "dev"
Requires-Dist: flake8>=4.0.0; extra == "dev"
Requires-Dist: mypy>=0.950; extra == "dev"
Dynamic: home-page
Dynamic: license-file
Dynamic: requires-python
